sakthi_make_it_easy/__init__.py
sakthi_make_it_easy/snake_game.py
sakthi_make_it_easy-1.0.0.dist-info/LICENSE
sakthi_make_it_easy-1.0.0.dist-info/METADATA
sakthi_make_it_easy-1.0.0.dist-info/WHEEL
sakthi_make_it_easy-1.0.0.dist-info/top_level.txt
sakthi_make_it_easy-1.0.0.dist-info/RECORD
