Metadata-Version: 2.1
Name: sakthi_make_it_easy
Version: 1.0.0
Summary: A modular Python-based Snake game using the turtle module.
Author-email: SakthiSelvan <ssakthitselvan7@gmail.com>
License: MIT
Project-URL: Homepage, https://github.com/yourusername/snake_game
Project-URL: Documentation, https://github.com/yourusername/snake_game/docs
Project-URL: Issue Tracker, https://github.com/yourusername/snake_game/issues
Keywords: snake-game,python-game,turtle-module,classic-game
Classifier: Programming Language :: Python :: 3
Classifier: License :: OSI Approved :: MIT License
Classifier: Operating System :: OS Independent
Classifier: Topic :: Games/Entertainment :: Arcade
Requires-Python: >=3.6
License-File: LICENSE
